dc_conversations/__init__.py
dc_conversations/conversation_migration.ipynb
dc_conversations/conversation_models.py
dc_conversations/conversations_classes.py
dc_conversations/conversations_router.py
dc_conversations/pydanticai_agents/__init__.py
dc_conversations/pydanticai_agents/agent_endpoint.py
dc_conversations/pydanticai_agents/conversation_agents.py
dc_conversations/pydanticai_agents/pydantic_ai_utils.py
dc_conversations-0.0.1.dist-info/METADATA
dc_conversations-0.0.1.dist-info/WHEEL
dc_conversations-0.0.1.dist-info/RECORD
